{
    "image_name": "wushu.mp4/109.jpg",
    "body_info": [
        {
            "box": [
                756,
                145,
                1077,
                1078,
                1
            ],
            "action_cls": "walk",
            "img_action_cls": [
                "climb",
                "other"
            ],
            "keypoints": [
                [
                    138.9398274421692,
                    96.99586694694823,
                    9.94085431098938
                ],
                [
                    159.57652035355568,
                    82.52184503122089,
                    9.991064667701721
                ],
                [
                    122.56038475036621,
                    84.66572905716008,
                    9.994902610778809
                ],
                [
                    182.18131065368652,
                    110.08489866918845,
                    9.151548743247986
                ],
                [
                    97.13787806034088,
                    112.6009784118945,
                    9.580581784248352
                ],
                [
                    222.67087841033936,
                    218.3211702402236,
                    6.913695335388184
                ],
                [
                    60.08273100852966,
                    235.61734524430193,
                    8.932667970657349
                ],
                [
                    39.060858726501465,
                    370.98992941069014,
                    8.685539960861206
                ],
                [
                    277.880784034729,
                    464.9356636014257,
                    9.25258457660675
                ],
                [
                    43.719168186187744,
                    474.6134093795834,
                    9.19373333454132
                ],
                [
                    218.78126430511475,
                    501.15782867591787,
                    3.5611802339553833
                ],
                [
                    116.31562232971191,
                    479.47311489369054,
                    4.635366499423981
                ],
                [
                    212.39260864257812,
                    668.1181386782356,
                    6.849414706230164
                ],
                [
                    130.05926609039307,
                    690.0291527199797,
                    8.348245620727539
                ],
                [
                    211.38412761688232,
                    820.5092233774865,
                    3.069669008255005
                ],
                [
                    159.05490112304688,
                    824.6121881498331,
                    3.9808976650238037
                ]
            ],
            "adjacent_keypoints": [
                [
                    [
                        218,
                        501
                    ],
                    [
                        222,
                        218
                    ]
                ],
                [
                    [
                        218,
                        501
                    ],
                    [
                        212,
                        668
                    ]
                ],
                [
                    [
                        212,
                        668
                    ],
                    [
                        211,
                        820
                    ]
                ],
                [
                    [
                        116,
                        479
                    ],
                    [
                        60,
                        235
                    ]
                ],
                [
                    [
                        39,
                        370
                    ],
                    [
                        60,
                        235
                    ]
                ],
                [
                    [
                        39,
                        370
                    ],
                    [
                        43,
                        474
                    ]
                ],
                [
                    [
                        116,
                        479
                    ],
                    [
                        130,
                        690
                    ]
                ],
                [
                    [
                        130,
                        690
                    ],
                    [
                        159,
                        824
                    ]
                ],
                [
                    [
                        222,
                        218
                    ],
                    [
                        60,
                        235
                    ]
                ],
                [
                    [
                        218,
                        501
                    ],
                    [
                        116,
                        479
                    ]
                ]
            ]
        }
    ],
    "face_info": [
        {
            "key_points": [
                [
                    853,
                    228
                ],
                [
                    853,
                    242
                ],
                [
                    852,
                    257
                ],
                [
                    853,
                    271
                ],
                [
                    857,
                    284
                ],
                [
                    863,
                    295
                ],
                [
                    872,
                    302
                ],
                [
                    881,
                    307
                ],
                [
                    892,
                    309
                ],
                [
                    902,
                    308
                ],
                [
                    911,
                    305
                ],
                [
                    921,
                    300
                ],
                [
                    928,
                    291
                ],
                [
                    932,
                    280
                ],
                [
                    935,
                    268
                ],
                [
                    937,
                    254
                ],
                [
                    939,
                    241
                ],
                [
                    867,
                    219
                ],
                [
                    873,
                    210
                ],
                [
                    881,
                    205
                ],
                [
                    889,
                    206
                ],
                [
                    898,
                    209
                ],
                [
                    904,
                    211
                ],
                [
                    912,
                    208
                ],
                [
                    920,
                    208
                ],
                [
                    927,
                    214
                ],
                [
                    931,
                    225
                ],
                [
                    898,
                    222
                ],
                [
                    898,
                    228
                ],
                [
                    897,
                    234
                ],
                [
                    897,
                    241
                ],
                [
                    888,
                    251
                ],
                [
                    892,
                    252
                ],
                [
                    897,
                    253
                ],
                [
                    901,
                    252
                ],
                [
                    906,
                    251
                ],
                [
                    875,
                    227
                ],
                [
                    879,
                    225
                ],
                [
                    883,
                    225
                ],
                [
                    888,
                    227
                ],
                [
                    883,
                    227
                ],
                [
                    879,
                    227
                ],
                [
                    909,
                    228
                ],
                [
                    913,
                    226
                ],
                [
                    917,
                    226
                ],
                [
                    921,
                    228
                ],
                [
                    917,
                    228
                ],
                [
                    913,
                    228
                ],
                [
                    879,
                    269
                ],
                [
                    886,
                    264
                ],
                [
                    892,
                    261
                ],
                [
                    896,
                    262
                ],
                [
                    900,
                    261
                ],
                [
                    906,
                    264
                ],
                [
                    911,
                    270
                ],
                [
                    906,
                    273
                ],
                [
                    900,
                    274
                ],
                [
                    896,
                    274
                ],
                [
                    891,
                    274
                ],
                [
                    886,
                    272
                ],
                [
                    882,
                    268
                ],
                [
                    892,
                    265
                ],
                [
                    896,
                    265
                ],
                [
                    900,
                    265
                ],
                [
                    909,
                    269
                ],
                [
                    900,
                    269
                ],
                [
                    896,
                    270
                ],
                [
                    892,
                    269
                ]
            ],
            "face_coordinate": [
                844,
                172,
                941,
                306
            ],
            "expression": "happy",
            "attention_score": 0.855
        }
    ]
}