{
    "image_name": "wushu.mp4/226.jpg",
    "body_info": [
        {
            "box": [
                833,
                209,
                1115,
                1002,
                1
            ],
            "action_cls": "walk",
            "img_action_cls": [
                "climb",
                "other"
            ],
            "keypoints": [
                [
                    140.71558622213513,
                    64.04949426947125,
                    9.987433552742004
                ],
                [
                    156.4946887257335,
                    46.409690206673496,
                    9.9574214220047
                ],
                [
                    125.21111974611388,
                    47.986340407353296,
                    9.977445602416992
                ],
                [
                    174.55970472817896,
                    70.65845081790997,
                    7.0841383934021
                ],
                [
                    100.50229432556657,
                    69.91800985640022,
                    9.318007230758667
                ],
                [
                    67.98125219083094,
                    176.65152782756053,
                    8.542683720588684
                ],
                [
                    37.58731035085825,
                    308.84588691322665,
                    7.2164565324783325
                ],
                [
                    251.3818307918507,
                    384.2999168517483,
                    8.389559388160706
                ],
                [
                    50.972151578127686,
                    396.9804427887983,
                    8.793816566467285
                ],
                [
                    192.67323907915053,
                    564.7724927197596,
                    3.2527047395706177
                ],
                [
                    115.64962072686836,
                    579.3897874370502,
                    8.778682351112366
                ],
                [
                    187.3775891314496,
                    687.2583354020575,
                    7.542563080787659
                ],
                [
                    135.03782798955731,
                    696.8036941671068,
                    8.650130033493042
                ]
            ],
            "adjacent_keypoints": [
                [
                    [
                        192,
                        564
                    ],
                    [
                        187,
                        687
                    ]
                ],
                [
                    [
                        37,
                        308
                    ],
                    [
                        67,
                        176
                    ]
                ],
                [
                    [
                        37,
                        308
                    ],
                    [
                        50,
                        396
                    ]
                ],
                [
                    [
                        115,
                        579
                    ],
                    [
                        135,
                        696
                    ]
                ]
            ]
        }
    ],
    "face_info": [
        {
            "key_points": [
                [
                    934,
                    258
                ],
                [
                    935,
                    270
                ],
                [
                    935,
                    282
                ],
                [
                    936,
                    293
                ],
                [
                    939,
                    303
                ],
                [
                    945,
                    311
                ],
                [
                    953,
                    317
                ],
                [
                    961,
                    322
                ],
                [
                    969,
                    324
                ],
                [
                    978,
                    324
                ],
                [
                    987,
                    320
                ],
                [
                    995,
                    316
                ],
                [
                    1002,
                    308
                ],
                [
                    1006,
                    299
                ],
                [
                    1008,
                    287
                ],
                [
                    1009,
                    275
                ],
                [
                    1010,
                    263
                ],
                [
                    948,
                    248
                ],
                [
                    952,
                    243
                ],
                [
                    957,
                    241
                ],
                [
                    963,
                    242
                ],
                [
                    968,
                    245
                ],
                [
                    979,
                    245
                ],
                [
                    985,
                    243
                ],
                [
                    991,
                    242
                ],
                [
                    996,
                    246
                ],
                [
                    1000,
                    252
                ],
                [
                    973,
                    255
                ],
                [
                    973,
                    261
                ],
                [
                    973,
                    267
                ],
                [
                    973,
                    273
                ],
                [
                    966,
                    280
                ],
                [
                    969,
                    281
                ],
                [
                    973,
                    282
                ],
                [
                    977,
                    281
                ],
                [
                    981,
                    280
                ],
                [
                    954,
                    257
                ],
                [
                    957,
                    256
                ],
                [
                    961,
                    256
                ],
                [
                    964,
                    258
                ],
                [
                    961,
                    258
                ],
                [
                    957,
                    258
                ],
                [
                    983,
                    258
                ],
                [
                    986,
                    256
                ],
                [
                    990,
                    257
                ],
                [
                    993,
                    259
                ],
                [
                    990,
                    259
                ],
                [
                    986,
                    259
                ],
                [
                    959,
                    295
                ],
                [
                    964,
                    291
                ],
                [
                    969,
                    289
                ],
                [
                    972,
                    290
                ],
                [
                    976,
                    289
                ],
                [
                    981,
                    291
                ],
                [
                    985,
                    296
                ],
                [
                    980,
                    299
                ],
                [
                    975,
                    300
                ],
                [
                    972,
                    301
                ],
                [
                    968,
                    300
                ],
                [
                    963,
                    299
                ],
                [
                    961,
                    295
                ],
                [
                    969,
                    293
                ],
                [
                    972,
                    293
                ],
                [
                    976,
                    293
                ],
                [
                    983,
                    296
                ],
                [
                    976,
                    295
                ],
                [
                    972,
                    295
                ],
                [
                    969,
                    295
                ]
            ],
            "face_coordinate": [
                926,
                210,
                1011,
                324
            ],
            "expression": "nature",
            "attention_score": 0.9772727272727273
        }
    ]
}