{
    "image_name": "wushu.mp4/250.jpg",
    "body_info": [
        {
            "box": [
                842,
                211,
                1155,
                1016,
                1
            ],
            "action_cls": "walk",
            "img_action_cls": [
                "climb",
                "other"
            ],
            "keypoints": [
                [
                    122.68928956203771,
                    71.18814247526629,
                    9.945765733718872
                ],
                [
                    139.75683014041087,
                    56.25809998696812,
                    9.953527450561523
                ],
                [
                    106.59287831666039,
                    55.80512361728892,
                    9.987240433692932
                ],
                [
                    158.52740360635224,
                    76.57508766011203,
                    8.7018221616745
                ],
                [
                    82.02279984584597,
                    73.45538495334048,
                    9.34108555316925
                ],
                [
                    192.690996412371,
                    176.79385736491648,
                    6.927899122238159
                ],
                [
                    46.107214193656795,
                    181.04698171627507,
                    8.219305276870728
                ],
                [
                    253.6882228444834,
                    288.28884108087396,
                    6.414628028869629
                ],
                [
                    310.99866236096517,
                    391.27380895852747,
                    3.5892996191978455
                ],
                [
                    188.083068097224,
                    573.5499484083625,
                    6.533145904541016
                ],
                [
                    98.65020633540192,
                    588.7541569960996,
                    8.936085104942322
                ],
                [
                    187.62631406940395,
                    702.011260194576,
                    4.783603847026825
                ],
                [
                    131.2786316320544,
                    709.3661553806133,
                    6.434913277626038
                ]
            ],
            "adjacent_keypoints": [
                [
                    [
                        253,
                        288
                    ],
                    [
                        192,
                        176
                    ]
                ],
                [
                    [
                        253,
                        288
                    ],
                    [
                        310,
                        391
                    ]
                ],
                [
                    [
                        188,
                        573
                    ],
                    [
                        187,
                        702
                    ]
                ],
                [
                    [
                        98,
                        588
                    ],
                    [
                        131,
                        709
                    ]
                ],
                [
                    [
                        192,
                        176
                    ],
                    [
                        46,
                        181
                    ]
                ]
            ]
        }
    ],
    "face_info": [
        {
            "key_points": [
                [
                    925,
                    262
                ],
                [
                    924,
                    274
                ],
                [
                    924,
                    286
                ],
                [
                    924,
                    297
                ],
                [
                    927,
                    308
                ],
                [
                    933,
                    316
                ],
                [
                    941,
                    323
                ],
                [
                    948,
                    329
                ],
                [
                    957,
                    332
                ],
                [
                    966,
                    332
                ],
                [
                    975,
                    329
                ],
                [
                    985,
                    324
                ],
                [
                    992,
                    316
                ],
                [
                    997,
                    307
                ],
                [
                    999,
                    295
                ],
                [
                    1000,
                    284
                ],
                [
                    1001,
                    273
                ],
                [
                    941,
                    251
                ],
                [
                    945,
                    246
                ],
                [
                    952,
                    245
                ],
                [
                    958,
                    247
                ],
                [
                    964,
                    251
                ],
                [
                    974,
                    252
                ],
                [
                    979,
                    249
                ],
                [
                    985,
                    249
                ],
                [
                    991,
                    253
                ],
                [
                    994,
                    259
                ],
                [
                    966,
                    265
                ],
                [
                    965,
                    271
                ],
                [
                    965,
                    276
                ],
                [
                    964,
                    282
                ],
                [
                    957,
                    290
                ],
                [
                    961,
                    291
                ],
                [
                    964,
                    292
                ],
                [
                    968,
                    291
                ],
                [
                    971,
                    291
                ],
                [
                    945,
                    266
                ],
                [
                    949,
                    265
                ],
                [
                    953,
                    266
                ],
                [
                    957,
                    268
                ],
                [
                    953,
                    269
                ],
                [
                    949,
                    268
                ],
                [
                    975,
                    269
                ],
                [
                    979,
                    267
                ],
                [
                    982,
                    268
                ],
                [
                    986,
                    270
                ],
                [
                    982,
                    270
                ],
                [
                    978,
                    270
                ],
                [
                    949,
                    305
                ],
                [
                    954,
                    300
                ],
                [
                    960,
                    298
                ],
                [
                    963,
                    300
                ],
                [
                    966,
                    299
                ],
                [
                    970,
                    301
                ],
                [
                    975,
                    305
                ],
                [
                    970,
                    308
                ],
                [
                    965,
                    309
                ],
                [
                    962,
                    309
                ],
                [
                    958,
                    309
                ],
                [
                    954,
                    307
                ],
                [
                    952,
                    305
                ],
                [
                    959,
                    303
                ],
                [
                    962,
                    304
                ],
                [
                    965,
                    304
                ],
                [
                    973,
                    305
                ],
                [
                    965,
                    303
                ],
                [
                    962,
                    303
                ],
                [
                    959,
                    303
                ]
            ],
            "face_coordinate": [
                914,
                216,
                1012,
                330
            ],
            "expression": "nature",
            "attention_score": 0.9572727272727273
        }
    ]
}