{
    "image_name": "wushu.mp4/68.jpg",
    "body_info": [
        {
            "box": [
                778,
                161,
                1069,
                1079,
                1
            ],
            "action_cls": "phone",
            "img_action_cls": [
                "stand",
                "other"
            ],
            "keypoints": [
                [
                    130.01062954090872,
                    93.69286492045842,
                    9.990764856338501
                ],
                [
                    147.24977360464712,
                    75.18202011321486,
                    9.98995840549469
                ],
                [
                    110.4983247761908,
                    77.34848885990573,
                    9.985559582710266
                ],
                [
                    169.72943925032567,
                    97.5711549137926,
                    5.102283954620361
                ],
                [
                    86.33502224654889,
                    102.34062250603198,
                    8.449721336364746
                ],
                [
                    203.5998339966507,
                    197.62755024002257,
                    5.569473505020142
                ]
            ],
            "adjacent_keypoints": []
        }
    ],
    "face_info": [
        {
            "key_points": [
                [
                    863,
                    240
                ],
                [
                    864,
                    253
                ],
                [
                    865,
                    266
                ],
                [
                    866,
                    279
                ],
                [
                    869,
                    291
                ],
                [
                    875,
                    300
                ],
                [
                    884,
                    308
                ],
                [
                    893,
                    314
                ],
                [
                    903,
                    317
                ],
                [
                    913,
                    317
                ],
                [
                    923,
                    313
                ],
                [
                    933,
                    307
                ],
                [
                    940,
                    299
                ],
                [
                    945,
                    288
                ],
                [
                    947,
                    274
                ],
                [
                    948,
                    260
                ],
                [
                    950,
                    247
                ],
                [
                    880,
                    229
                ],
                [
                    885,
                    223
                ],
                [
                    891,
                    221
                ],
                [
                    899,
                    221
                ],
                [
                    905,
                    224
                ],
                [
                    916,
                    224
                ],
                [
                    922,
                    221
                ],
                [
                    930,
                    221
                ],
                [
                    936,
                    224
                ],
                [
                    941,
                    231
                ],
                [
                    910,
                    235
                ],
                [
                    910,
                    241
                ],
                [
                    910,
                    246
                ],
                [
                    910,
                    252
                ],
                [
                    900,
                    261
                ],
                [
                    904,
                    262
                ],
                [
                    909,
                    263
                ],
                [
                    914,
                    263
                ],
                [
                    918,
                    263
                ],
                [
                    887,
                    237
                ],
                [
                    891,
                    235
                ],
                [
                    895,
                    236
                ],
                [
                    900,
                    238
                ],
                [
                    895,
                    238
                ],
                [
                    891,
                    238
                ],
                [
                    920,
                    239
                ],
                [
                    924,
                    236
                ],
                [
                    928,
                    236
                ],
                [
                    933,
                    239
                ],
                [
                    929,
                    239
                ],
                [
                    924,
                    239
                ],
                [
                    891,
                    279
                ],
                [
                    898,
                    273
                ],
                [
                    905,
                    270
                ],
                [
                    908,
                    271
                ],
                [
                    913,
                    271
                ],
                [
                    919,
                    274
                ],
                [
                    924,
                    281
                ],
                [
                    918,
                    286
                ],
                [
                    912,
                    288
                ],
                [
                    907,
                    288
                ],
                [
                    903,
                    288
                ],
                [
                    897,
                    285
                ],
                [
                    893,
                    278
                ],
                [
                    904,
                    275
                ],
                [
                    908,
                    275
                ],
                [
                    912,
                    276
                ],
                [
                    922,
                    280
                ],
                [
                    912,
                    283
                ],
                [
                    908,
                    282
                ],
                [
                    904,
                    282
                ]
            ],
            "face_coordinate": [
                850,
                183,
                953,
                322
            ],
            "expression": "happy",
            "attention_score": 0.865
        }
    ]
}